xia_module_pypi/__init__.py
xia_module_pypi/gcp.py
xia_module_pypi/pypi.py
xia_module_pypi/templates/gcp-module-pypi/activate/main.tf
xia_module_pypi/templates/gcp-module-pypi/activate/variables.tf
xia_module_pypi/templates/gcp-module-pypi/base/activate.tf
xia_module_pypi/templates/gcp-module-pypi/base/main.tf
xia_module_pypi/templates/gcp-module-pypi/cicd/github/workflow.yml
xia_module_pypi/templates/gcp-module-pypi/cicd/github/actions/publish-pypi-gcp/action.yml
xia_module_pypi/templates/gcp-module-pypi/init/.gitignore
xia_module_pypi/templates/gcp-module-pypi/init/LICENSE
xia_module_pypi/templates/gcp-module-pypi/init/README.rst
xia_module_pypi/templates/gcp-module-pypi/init/requirements.txt
xia_module_pypi/templates/gcp-module-pypi/init/setup.py
xia_module_pypi/templates/gcp-module-pypi/module/main.tf
xia_module_pypi/templates/gcp-module-pypi/module/variables.tf
xia_module_pypi/templates/gcp-module-pypi/template/__init__.py.jinja
xia_module_pypi/templates/module-pypi/cicd/github/workflow.yml
xia_module_pypi/templates/module-pypi/cicd/github/actions/publish-pypi/action.yml
xia_module_pypi/templates/module-pypi/init/.gitignore
xia_module_pypi/templates/module-pypi/init/LICENSE
xia_module_pypi/templates/module-pypi/init/README.rst
xia_module_pypi/templates/module-pypi/init/requirements.txt
xia_module_pypi/templates/module-pypi/init/setup.py
xia_module_pypi/templates/module-pypi/template/__init__.py.jinja
xia_module_pypi-0.0.11.dist-info/LICENSE
xia_module_pypi-0.0.11.dist-info/METADATA
xia_module_pypi-0.0.11.dist-info/WHEEL
xia_module_pypi-0.0.11.dist-info/top_level.txt
xia_module_pypi-0.0.11.dist-info/RECORD
