Metadata-Version: 2.1
Name: xia-module-pypi
Version: 0.0.11
Requires-Python: >=3.9
License-File: LICENSE
Requires-Dist: PyYAML
